filecache/__init__.py
filecache/main.py
filecacher-0.0.0.dist-info/METADATA
filecacher-0.0.0.dist-info/WHEEL
filecacher-0.0.0.dist-info/RECORD
